rfd/__init__.py
rfd/__main__.py
rfd/api.py
rfd/cli.py
rfd/posts.py
rfd/scores.py
rfd/threads.py
rfd/utils.py
rfd-0.9.0.dist-info/entry_points.txt
rfd-0.9.0.dist-info/LICENSE
rfd-0.9.0.dist-info/WHEEL
rfd-0.9.0.dist-info/METADATA
rfd-0.9.0.dist-info/RECORD
