Metadata-Version: 2.1
Name: rfd
Version: 0.9.0
Summary: view RedFlagDeals.com from the command line
License: GPL-3.0-or-later
Author: Dave Gallant
Author-email: davegallant@gmail.com
Requires-Python: >=3.6,<4.0
Classifier: License :: OSI Approved :: GNU General Public License v3 or later (GPLv3+)
Classifier: Programming Language :: Python :: 3
Classifier: Programming Language :: Python :: 3.10
Classifier: Programming Language :: Python :: 3.6
Classifier: Programming Language :: Python :: 3.7
Classifier: Programming Language :: Python :: 3.8
Classifier: Programming Language :: Python :: 3.9
Requires-Dist: beautifulsoup4 (>=4.10.1)
Requires-Dist: click (>=7.0)
Requires-Dist: colorama (>=0.4.3)
Requires-Dist: requests (>=2.22.0)
Requires-Dist: soupsieve (<3.0)
